ansys/scadeone/core/__init__.py
ansys/scadeone/core/cli.py
ansys/scadeone/core/interfaces.py
ansys/scadeone/core/job.py
ansys/scadeone/core/project.py
ansys/scadeone/core/py.typed
ansys/scadeone/core/scadeone.py
ansys/scadeone/core/common/__init__.py
ansys/scadeone/core/common/dotnet.py
ansys/scadeone/core/common/exception.py
ansys/scadeone/core/common/logger.py
ansys/scadeone/core/common/storage.py
ansys/scadeone/core/common/versioning.py
ansys/scadeone/core/common/versions.json
ansys/scadeone/core/libs/test-results-schema.json
ansys/scadeone/core/libs/versions.txt
ansys/scadeone/core/libs/dotnet/ANSYS.SONE.Core.Toolkit.Logging.dll
ansys/scadeone/core/libs/dotnet/ANSYS.SONE.Infrastructure.Services.Serialization.BNF.Parsing.dll
ansys/scadeone/core/libs/dotnet/FSharp.Core.dll
ansys/scadeone/core/libs/dotnet/FsLexYacc.Runtime.dll
ansys/scadeone/core/libs/linux-x64/libswan_sd.so
ansys/scadeone/core/libs/win-x64/swan_sd.dll
ansys/scadeone/core/model/__init__.py
ansys/scadeone/core/model/dotnet.py
ansys/scadeone/core/model/loader.py
ansys/scadeone/core/model/model.py
ansys/scadeone/core/model/parser.py
ansys/scadeone/core/model/pyofast.py
ansys/scadeone/core/svc/__init__.py
ansys/scadeone/core/svc/build_system.py
ansys/scadeone/core/svc/swan_printer.py
ansys/scadeone/core/svc/common/renderer.py
ansys/scadeone/core/svc/common/templates/swan_config_template.h
ansys/scadeone/core/svc/fmu/__init__.py
ansys/scadeone/core/svc/fmu/fmu_export.py
ansys/scadeone/core/svc/fmu/model.png
ansys/scadeone/core/svc/fmu/includes/FMI/fmi2FunctionTypes.h
ansys/scadeone/core/svc/fmu/includes/FMI/fmi2Functions.h
ansys/scadeone/core/svc/fmu/includes/FMI/fmi2TypesPlatform.h
ansys/scadeone/core/svc/fmu/templates/FMI_v2.0_template.c
ansys/scadeone/core/svc/fmu/templates/FMI_v2.0_template.j2
ansys/scadeone/core/svc/fmu/templates/swan_config_template.h
ansys/scadeone/core/svc/generated_code/__init__.py
ansys/scadeone/core/svc/generated_code/generated_code.py
ansys_scadeone_core-0.7.1.dist-info/entry_points.txt
ansys_scadeone_core-0.7.1.dist-info/licenses/LICENSE
ansys_scadeone_core-0.7.1.dist-info/WHEEL
ansys_scadeone_core-0.7.1.dist-info/METADATA
ansys_scadeone_core-0.7.1.dist-info/RECORD
