Metadata-Version: 2.4
Name: ansys-scadeone-core
Version: 0.7.1
Summary: Python interface for Ansys Scade One
Author-email: "ANSYS, Inc." <pyansys.core@ansys.com>
Maintainer-email: "ANSYS, Inc." <pyansys.core@ansys.com>
Requires-Python: >=3.10,<4
Classifier: Development Status :: 4 - Beta
Classifier: Intended Audience :: Developers
Classifier: Intended Audience :: Science/Research
Classifier: Topic :: Software Development :: Libraries
Classifier: Topic :: Scientific/Engineering :: Information Analysis
Classifier: License :: OSI Approved :: MIT License
Classifier: Operating System :: OS Independent
Classifier: Programming Language :: Python :: 3.10
Classifier: Programming Language :: Python :: 3.11
Classifier: Programming Language :: Python :: 3.12
License-File: LICENSE
Requires-Dist: Jinja2>=3.1.4
Requires-Dist: jsonschema>=4.23.0
Requires-Dist: platformdirs>=4.3.2
Requires-Dist: pyparsing>=3.1.4
Requires-Dist: pythonnet>=3.0.4
Requires-Dist: typing_extensions>=4.12.2
Requires-Dist: lark>=1.2.2
Requires-Dist: codespell==2.2.6 ; extra == "checks"
Requires-Dist: ruff==0.8.2 ; extra == "checks"
Requires-Dist: vale==3.9.1 ; extra == "checks"
Requires-Dist: pre-commit==4.0.1 ; extra == "checks"
Requires-Dist: ansys-sphinx-theme==1.2.4 ; extra == "doc"
Requires-Dist: pillow>=10.1 ; extra == "doc"
Requires-Dist: sphinx==8.1.3 ; extra == "doc"
Requires-Dist: sphinx-copybutton==0.5.2 ; extra == "doc"
Requires-Dist: sphinx-autobuild==2024.10.3 ; extra == "doc"
Requires-Dist: sphinx-autodoc-typehints==2.5.0 ; extra == "doc"
Requires-Dist: sphinx-design==0.6.1 ; extra == "doc"
Requires-Dist: pytest-sphinx==0.5.0 ; extra == "doc"
Requires-Dist: sphinx-jinja>=2.0.0 ; extra == "doc"
Requires-Dist: numpydoc==1.8.0 ; extra == "doc"
Requires-Dist: attrs==24.2.0 ; extra == "frozen-dependencies"
Requires-Dist: cffi==1.17.1 ; extra == "frozen-dependencies"
Requires-Dist: clr-loader==0.2.6 ; extra == "frozen-dependencies"
Requires-Dist: jsonschema-specifications==2023.12.1 ; extra == "frozen-dependencies"
Requires-Dist: MarkupSafe==2.1.5 ; extra == "frozen-dependencies"
Requires-Dist: pycparser==2.22 ; extra == "frozen-dependencies"
Requires-Dist: referencing==0.35.1 ; extra == "frozen-dependencies"
Requires-Dist: rpds-py==0.20.0 ; extra == "frozen-dependencies"
Requires-Dist: Jinja2==3.1.4 ; extra == "frozen-dependencies"
Requires-Dist: jsonschema==4.23.0 ; extra == "frozen-dependencies"
Requires-Dist: platformdirs==4.3.2 ; extra == "frozen-dependencies"
Requires-Dist: pyparsing==3.1.4 ; extra == "frozen-dependencies"
Requires-Dist: pythonnet==3.0.4 ; extra == "frozen-dependencies"
Requires-Dist: typing_extensions==4.12.2 ; extra == "frozen-dependencies"
Requires-Dist: lark==1.2.2 ; extra == "frozen-dependencies"
Requires-Dist: pytest>=7.1.0 ; extra == "tests"
Requires-Dist: pytest-cov>=3.0.0 ; extra == "tests"
Requires-Dist: click>=8.1.7 ; extra == "tests"
Requires-Dist: fmpy>=0.3.21 ; extra == "tests"
Project-URL: documentation, https://scadeone.docs.pyansys.com
Project-URL: issues, https://github.com/ansys/pyscadeone/issues
Project-URL: source, https://github.com/ansys/pyscadeone
Project-URL: tracker, https://github.com/ansys/pyscadeone/issues
Provides-Extra: checks
Provides-Extra: doc
Provides-Extra: frozen-dependencies
Provides-Extra: tests
